{
  "ApplicationId": "string",
  "_BilledSize": "real",
  "ClusterDnsName": "string",
  "ClusterTenantId": "string",
  "CompletionTime": "datetime",
  "Host": "string",
  "IpAddress": "string",
  "_IsBillable": "string",
  "JobId": "string",
  "JobResult": "string",
  "Region": "string",
  "_ResourceId": "string",
  "Role": "string",
  "SourceSystem": "string",
  "StageIds": "string",
  "SubmissionTime": "datetime",
  "_SubscriptionId": "string",
  "TenantId": "string",
  "TimeGenerated": "datetime",
  "Type": "string",
  "UserSubscriptionId": "string"
}
