{
  "AccessRuleVersion": "string",
  "AppId": "string",
  "_BilledSize": "real",
  "Category": "string",
  "Count": "int",
  "DestinationEmailAddress": "string",
  "DestinationFqdn": "string",
  "DestinationParameters": "string",
  "DestinationPhoneNumber": "string",
  "DestinationPort": "string",
  "DestinationProtocol": "string",
  "DestinationResourceId": "string",
  "_IsBillable": "string",
  "Location": "string",
  "MatchedRule": "string",
  "OperationName": "string",
  "OperationVersion": "string",
  "Parameters": "string",
  "Profile": "string",
  "_ResourceId": "string",
  "ResultAction": "string",
  "ResultDescription": "string",
  "ResultDirection": "string",
  "RuleType": "string",
  "ServiceFqdn": "string",
  "ServiceResourceId": "string",
  "SourceAppId": "string",
  "SourceIpAddress": "string",
  "SourceParameters": "string",
  "SourcePerimeterGuids": "string",
  "SourcePort": "string",
  "SourceProtocol": "string",
  "SourceResourceId": "string",
  "SourceSystem": "string",
  "_SubscriptionId": "string",
  "TenantId": "string",
  "TimeGenerated": "datetime",
  "TimeGeneratedEndTime": "datetime",
  "TrafficType": "string",
  "Type": "string"
}
